receipt_generator/__init__.py
receipt_generator/cli.py
receipt_generator/generator.py
CUB_receipt_generator-0.1.0.dist-info/METADATA
CUB_receipt_generator-0.1.0.dist-info/WHEEL
CUB_receipt_generator-0.1.0.dist-info/entry_points.txt
CUB_receipt_generator-0.1.0.dist-info/top_level.txt
CUB_receipt_generator-0.1.0.dist-info/RECORD
