Metadata-Version: 2.1
Name: CUB_receipt_generator
Version: 0.1.0
Summary: A package for generating receipts from order data.
Author: Alex
Author-email: haylarrr@yandex.ru
